{
  "movieId": 10528,
  "title": "Sherlock Holmes",
  "generatedAt": "2026-02-07T10:31:07.718Z",
  "reviews": [
    "Downey reinvents Holmes with swagger",
    "Action packed Victorian detective brilliance",
    "Witty banter steals every scene",
    "Ritchie's direction feels perfectly crafted",
    "Chemistry between leads is electric",
    "Visually stunning period piece executed",
    "Smart entertainment that actually delivers",
    "Fresh take on classic character",
    "Incredibly satisfying mystery adventure film",
    "Downey's charisma carries entire movie",
    "Stylish reboot exceeds all expectations",
    "Clever writing makes Holmes accessible",
    "Action sequences are expertly choreographed",
    "Perfect blend of brains and",
    "Modern energy revitalizes tired franchise",
    "Law's Watson provides excellent counterbalance",
    "Steampunk aesthetic enhances Victorian atmosphere",
    "Engaging from first frame forward",
    "Surprisingly deep beneath flashy surface",
    "Leaves you craving immediate sequel"
  ],
  "validation": {
    "totalReviews": 20,
    "validFiveWord": 20,
    "issues": []
  },
  "wordFrequency": {
    "downey": 1,
    "reinvents": 1,
    "holmes": 2,
    "swagger": 1,
    "action": 2,
    "packed": 1,
    "victorian": 2,
    "detective": 1,
    "brilliance": 1,
    "witty": 1,
    "banter": 1,
    "steals": 1,
    "ritchie's": 1,
    "direction": 1,
    "perfectly": 1,
    "crafted": 1,
    "chemistry": 1,
    "leads": 1,
    "electric": 1,
    "visually": 1,
    "stunning": 1,
    "period": 1,
    "piece": 1,
    "executed": 1,
    "smart": 1,
    "entertainment": 1,
    "actually": 1,
    "delivers": 1,
    "fresh": 1,
    "classic": 1,
    "incredibly": 1,
    "satisfying": 1,
    "mystery": 1,
    "adventure": 1,
    "downey's": 1,
    "charisma": 1,
    "carries": 1,
    "entire": 1,
    "stylish": 1,
    "reboot": 1,
    "exceeds": 1,
    "expectations": 1,
    "clever": 1,
    "writing": 1,
    "accessible": 1,
    "sequences": 1,
    "expertly": 1,
    "choreographed": 1,
    "perfect": 1,
    "blend": 1,
    "brains": 1,
    "modern": 1,
    "energy": 1,
    "revitalizes": 1,
    "tired": 1,
    "franchise": 1,
    "law's": 1,
    "watson": 1,
    "provides": 1,
    "excellent": 1,
    "counterbalance": 1,
    "steampunk": 1,
    "aesthetic": 1,
    "enhances": 1,
    "atmosphere": 1,
    "engaging": 1,
    "first": 1,
    "frame": 1,
    "forward": 1,
    "surprisingly": 1,
    "deep": 1,
    "beneath": 1,
    "flashy": 1,
    "surface": 1,
    "leaves": 1,
    "craving": 1,
    "immediate": 1,
    "sequel": 1
  },
  "topWords": [
    "holmes",
    "action",
    "victorian",
    "downey",
    "reinvents"
  ],
  "processedAt": "2026-02-07T10:59:03.060Z"
}