{
  "movieId": 18491,
  "title": "Neon Genesis Evangelion: The End of Evangelion",
  "generatedAt": "2026-02-07T10:50:23.953Z",
  "reviews": [
    "Transcendent mindfuck of psychological cinema",
    "Devastatingly beautiful and utterly haunting",
    "Left me emotionally shattered completely",
    "Masterpiece that redefined anime forever",
    "Surreal nightmare fuel done brilliantly",
    "Still processing weeks after viewing",
    "Profoundly disturbing yet absolutely captivating",
    "Genius-level filmmaking meets existential dread",
    "Visually stunning psychological horror experience",
    "Mind-bending finale executed with perfection",
    "Controversial ending that divides audiences",
    "Artistic triumph wrapped in despair",
    "Uncomfortable introspection made beautifully cinematic",
    "Demanding watch that rewards patience",
    "Apocalyptic poetry rendered in animation",
    "Haunts dreams long after credits",
    "Challenging masterwork requiring multiple viewings",
    "Disturbing beauty that stays forever",
    "Visceral emotional experience unlike anything",
    "Brilliant madness captured on film"
  ],
  "validation": {
    "totalReviews": 20,
    "validFiveWord": 20,
    "issues": []
  },
  "wordFrequency": {
    "transcendent": 1,
    "mindfuck": 1,
    "psychological": 2,
    "cinema": 1,
    "devastatingly": 1,
    "beautiful": 1,
    "utterly": 1,
    "haunting": 1,
    "left": 1,
    "emotionally": 1,
    "shattered": 1,
    "masterpiece": 1,
    "redefined": 1,
    "anime": 1,
    "forever": 2,
    "surreal": 1,
    "nightmare": 1,
    "fuel": 1,
    "done": 1,
    "brilliantly": 1,
    "processing": 1,
    "weeks": 1,
    "viewing": 1,
    "profoundly": 1,
    "disturbing": 2,
    "yet": 1,
    "captivating": 1,
    "genius-level": 1,
    "filmmaking": 1,
    "meets": 1,
    "existential": 1,
    "dread": 1,
    "visually": 1,
    "stunning": 1,
    "horror": 1,
    "experience": 2,
    "mind-bending": 1,
    "finale": 1,
    "executed": 1,
    "perfection": 1,
    "controversial": 1,
    "divides": 1,
    "audiences": 1,
    "artistic": 1,
    "triumph": 1,
    "wrapped": 1,
    "despair": 1,
    "uncomfortable": 1,
    "introspection": 1,
    "beautifully": 1,
    "cinematic": 1,
    "demanding": 1,
    "rewards": 1,
    "patience": 1,
    "apocalyptic": 1,
    "poetry": 1,
    "rendered": 1,
    "animation": 1,
    "haunts": 1,
    "dreams": 1,
    "long": 1,
    "credits": 1,
    "challenging": 1,
    "masterwork": 1,
    "requiring": 1,
    "multiple": 1,
    "viewings": 1,
    "beauty": 1,
    "stays": 1,
    "visceral": 1,
    "emotional": 1,
    "unlike": 1,
    "anything": 1,
    "brilliant": 1,
    "madness": 1,
    "captured": 1
  },
  "topWords": [
    "psychological",
    "forever",
    "disturbing",
    "experience",
    "transcendent"
  ],
  "processedAt": "2026-02-07T10:59:03.359Z"
}