{
  "movieId": 505,
  "title": "Ant-Man",
  "generatedAt": "2026-02-07T07:17:48.690Z",
  "reviews": [
    "Surprisingly charming and genuinely entertaining",
    "Perfect blend humor and action",
    "Rudd's charisma carries entire film",
    "Small scale feels refreshingly intimate",
    "Visual effects are absolutely stunning",
    "Father daughter story surprisingly touching",
    "Comedy timing is absolutely perfect",
    "Exceeded all my low expectations",
    "Most underrated Marvel origin story",
    "Shrinking sequences are pure magic",
    "Heist elements work brilliantly here",
    "Corey Stoll makes menacing villain",
    "Family themes resonate deeply throughout",
    "Light hearted but emotionally satisfying",
    "Paul Rudd was perfectly cast",
    "Action scenes creatively use size",
    "Refreshing break from epic scale",
    "Clever script balances all elements",
    "Surprisingly heartfelt Marvel entry overall",
    "Left wanting immediate sequel immediately"
  ],
  "validation": {
    "totalReviews": 20,
    "validFiveWord": 20,
    "issues": []
  },
  "wordFrequency": {
    "surprisingly": 3,
    "charming": 1,
    "genuinely": 1,
    "entertaining": 1,
    "perfect": 2,
    "blend": 1,
    "humor": 1,
    "action": 2,
    "rudd's": 1,
    "charisma": 1,
    "carries": 1,
    "entire": 1,
    "small": 1,
    "scale": 2,
    "refreshingly": 1,
    "intimate": 1,
    "visual": 1,
    "effects": 1,
    "stunning": 1,
    "father": 1,
    "daughter": 1,
    "touching": 1,
    "comedy": 1,
    "timing": 1,
    "exceeded": 1,
    "low": 1,
    "expectations": 1,
    "underrated": 1,
    "marvel": 2,
    "origin": 1,
    "shrinking": 1,
    "sequences": 1,
    "pure": 1,
    "magic": 1,
    "heist": 1,
    "elements": 2,
    "work": 1,
    "brilliantly": 1,
    "here": 1,
    "corey": 1,
    "stoll": 1,
    "menacing": 1,
    "villain": 1,
    "family": 1,
    "themes": 1,
    "resonate": 1,
    "deeply": 1,
    "throughout": 1,
    "light": 1,
    "hearted": 1,
    "emotionally": 1,
    "satisfying": 1,
    "paul": 1,
    "rudd": 1,
    "perfectly": 1,
    "cast": 1,
    "creatively": 1,
    "use": 1,
    "size": 1,
    "refreshing": 1,
    "break": 1,
    "epic": 1,
    "clever": 1,
    "script": 1,
    "balances": 1,
    "heartfelt": 1,
    "entry": 1,
    "overall": 1,
    "left": 1,
    "wanting": 1,
    "immediate": 1,
    "sequel": 1,
    "immediately": 1
  },
  "topWords": [
    "surprisingly",
    "perfect",
    "action",
    "scale",
    "marvel"
  ],
  "processedAt": "2026-02-07T10:59:03.941Z"
}