{
  "movieId": 75780,
  "title": "Jack Reacher",
  "generatedAt": "2026-02-07T10:56:09.867Z",
  "reviews": [
    "Cruise delivers surprisingly grounded performance here",
    "Brutal action sequences feel authentically visceral",
    "Character study disguised as thriller",
    "Old school detective work refreshingly methodical",
    "Violence has genuine weight and consequence",
    "Perfectly paced investigation keeps you engaged",
    "Reacher's intimidation factor absolutely works here",
    "Solid adaptation respects source material well",
    "Mystery unravels with satisfying logical precision",
    "Cruise's physicality convinces despite height difference",
    "Gritty tone elevates standard revenge plot",
    "Supporting cast provides excellent dramatic foundation",
    "Action choreography emphasizes brutality over spectacle",
    "Werner Herzog's villain chills to bone",
    "Investigation feels genuinely procedural and smart",
    "Character's moral code drives compelling narrative",
    "Surprisingly thoughtful approach to vigilante justice",
    "Tension builds steadily without rushing payoffs",
    "Realistic combat makes every fight meaningful",
    "Exceeds expectations for franchise starter film"
  ],
  "validation": {
    "totalReviews": 20,
    "validFiveWord": 1,
    "issues": [
      "Review 1 has 6 words: \"Cruise delivers surprisingly grounded performance here\"",
      "Review 2 has 6 words: \"Brutal action sequences feel authentically visceral\"",
      "Review 4 has 6 words: \"Old school detective work refreshingly methodical\"",
      "Review 5 has 6 words: \"Violence has genuine weight and consequence\"",
      "Review 6 has 6 words: \"Perfectly paced investigation keeps you engaged\"",
      "Review 7 has 6 words: \"Reacher's intimidation factor absolutely works here\"",
      "Review 8 has 6 words: \"Solid adaptation respects source material well\"",
      "Review 9 has 6 words: \"Mystery unravels with satisfying logical precision\"",
      "Review 10 has 6 words: \"Cruise's physicality convinces despite height difference\"",
      "Review 11 has 6 words: \"Gritty tone elevates standard revenge plot\"",
      "Review 12 has 6 words: \"Supporting cast provides excellent dramatic foundation\"",
      "Review 13 has 6 words: \"Action choreography emphasizes brutality over spectacle\"",
      "Review 14 has 6 words: \"Werner Herzog's villain chills to bone\"",
      "Review 15 has 6 words: \"Investigation feels genuinely procedural and smart\"",
      "Review 16 has 6 words: \"Character's moral code drives compelling narrative\"",
      "Review 17 has 6 words: \"Surprisingly thoughtful approach to vigilante justice\"",
      "Review 18 has 6 words: \"Tension builds steadily without rushing payoffs\"",
      "Review 19 has 6 words: \"Realistic combat makes every fight meaningful\"",
      "Review 20 has 6 words: \"Exceeds expectations for franchise starter film\""
    ]
  },
  "wordFrequency": {
    "cruise": 1,
    "delivers": 1,
    "surprisingly": 2,
    "grounded": 1,
    "performance": 1,
    "here": 2,
    "brutal": 1,
    "action": 2,
    "sequences": 1,
    "authentically": 1,
    "visceral": 1,
    "study": 1,
    "disguised": 1,
    "thriller": 1,
    "old": 1,
    "school": 1,
    "detective": 1,
    "work": 1,
    "refreshingly": 1,
    "methodical": 1,
    "violence": 1,
    "genuine": 1,
    "weight": 1,
    "consequence": 1,
    "perfectly": 1,
    "paced": 1,
    "investigation": 2,
    "engaged": 1,
    "reacher's": 1,
    "intimidation": 1,
    "factor": 1,
    "works": 1,
    "solid": 1,
    "adaptation": 1,
    "respects": 1,
    "source": 1,
    "material": 1,
    "well": 1,
    "mystery": 1,
    "unravels": 1,
    "satisfying": 1,
    "logical": 1,
    "precision": 1,
    "cruise's": 1,
    "physicality": 1,
    "convinces": 1,
    "despite": 1,
    "height": 1,
    "difference": 1,
    "gritty": 1,
    "tone": 1,
    "elevates": 1,
    "standard": 1,
    "revenge": 1,
    "supporting": 1,
    "cast": 1,
    "provides": 1,
    "excellent": 1,
    "dramatic": 1,
    "foundation": 1,
    "choreography": 1,
    "emphasizes": 1,
    "brutality": 1,
    "spectacle": 1,
    "werner": 1,
    "herzog's": 1,
    "villain": 1,
    "chills": 1,
    "bone": 1,
    "genuinely": 1,
    "procedural": 1,
    "smart": 1,
    "character's": 1,
    "moral": 1,
    "code": 1,
    "drives": 1,
    "compelling": 1,
    "narrative": 1,
    "thoughtful": 1,
    "approach": 1,
    "vigilante": 1,
    "justice": 1,
    "tension": 1,
    "builds": 1,
    "steadily": 1,
    "without": 1,
    "rushing": 1,
    "payoffs": 1,
    "realistic": 1,
    "combat": 1,
    "fight": 1,
    "meaningful": 1,
    "exceeds": 1,
    "expectations": 1,
    "franchise": 1,
    "starter": 1
  },
  "topWords": [
    "surprisingly",
    "here",
    "action",
    "investigation",
    "cruise"
  ],
  "processedAt": "2026-02-07T10:59:04.364Z"
}