{
  "movieId": 301528,
  "title": "Toy Story 4",
  "generatedAt": "2026-02-07T07:12:29.171Z",
  "reviews": [
    "Emotional masterpiece concludes beloved franchise perfectly",
    "Tears guaranteed in final farewell",
    "Pixar's storytelling brilliance shines brightest",
    "Heartwarming conclusion exceeds all expectations",
    "Adult themes wrapped beautifully together",
    "Woody's journey reaches satisfying conclusion",
    "Animation quality absolutely mind blowing",
    "Childhood nostalgia hits incredibly hard",
    "Perfect ending deserves standing ovation",
    "Tissues required for emotional moments",
    "Voice acting delivers outstanding performances",
    "Bittersweet finale leaves lasting impact",
    "Visual spectacle combined with heart",
    "Grown ups will cry harder",
    "Franchise finale executed with perfection",
    "Emotional depth surprises even adults",
    "Childhood memories beautifully brought back",
    "Outstanding conclusion to epic saga",
    "Pixar magic at absolute peak",
    "Unforgettable farewell to beloved characters"
  ],
  "validation": {
    "totalReviews": 20,
    "validFiveWord": 19,
    "issues": [
      "Review 1 has 6 words: \"Emotional masterpiece concludes beloved franchise perfectly\""
    ]
  },
  "wordFrequency": {
    "emotional": 3,
    "masterpiece": 1,
    "concludes": 1,
    "beloved": 2,
    "franchise": 2,
    "perfectly": 1,
    "tears": 1,
    "guaranteed": 1,
    "final": 1,
    "farewell": 2,
    "pixar's": 1,
    "storytelling": 1,
    "brilliance": 1,
    "shines": 1,
    "brightest": 1,
    "heartwarming": 1,
    "conclusion": 3,
    "exceeds": 1,
    "expectations": 1,
    "adult": 1,
    "themes": 1,
    "wrapped": 1,
    "beautifully": 2,
    "together": 1,
    "woody's": 1,
    "journey": 1,
    "reaches": 1,
    "satisfying": 1,
    "animation": 1,
    "quality": 1,
    "mind": 1,
    "blowing": 1,
    "childhood": 2,
    "nostalgia": 1,
    "hits": 1,
    "incredibly": 1,
    "hard": 1,
    "perfect": 1,
    "deserves": 1,
    "standing": 1,
    "ovation": 1,
    "tissues": 1,
    "required": 1,
    "moments": 1,
    "voice": 1,
    "delivers": 1,
    "outstanding": 2,
    "performances": 1,
    "bittersweet": 1,
    "finale": 2,
    "leaves": 1,
    "lasting": 1,
    "impact": 1,
    "visual": 1,
    "spectacle": 1,
    "combined": 1,
    "heart": 1,
    "grown": 1,
    "ups": 1,
    "cry": 1,
    "harder": 1,
    "executed": 1,
    "perfection": 1,
    "depth": 1,
    "surprises": 1,
    "adults": 1,
    "memories": 1,
    "brought": 1,
    "back": 1,
    "epic": 1,
    "saga": 1,
    "pixar": 1,
    "magic": 1,
    "absolute": 1,
    "peak": 1,
    "unforgettable": 1,
    "mind-blowing": 1
  },
  "topWords": [
    "emotional",
    "conclusion",
    "beloved",
    "franchise",
    "farewell"
  ],
  "processedAt": "2026-02-07T10:59:03.578Z"
}