{
  "movieId": 546554,
  "title": "Knives Out",
  "generatedAt": "2026-02-07T10:17:27.561Z",
  "reviews": [
    "Brilliant whodunit with stellar ensemble cast",
    "Mystery crafted to absolute perfection here",
    "Daniel Craig's accent steals every scene",
    "Witty dialogue keeps you constantly engaged",
    "Plot twists genuinely shocked me completely",
    "Modern Agatha Christie done absolutely right",
    "Cleverly subverts all murder mystery expectations",
    "Ana de Armas delivers phenomenal breakthrough performance",
    "Sharp social commentary disguised as entertainment",
    "Rian Johnson proves his directorial genius",
    "Every character feels perfectly developed throughout",
    "Rewatchable mystery reveals new clues constantly",
    "Satisfying conclusion ties everything together beautifully",
    "Humor balances suspense in perfect harmony",
    "Christopher Plummer's final performance shines bright",
    "Class warfare themes executed with subtlety",
    "Benoit Blanc deserves his own franchise",
    "Smart script respects audience's intelligence completely",
    "Visual storytelling enhances every single scene",
    "Deserves all the critical acclaim received"
  ],
  "validation": {
    "totalReviews": 20,
    "validFiveWord": 0,
    "issues": [
      "Review 1 has 6 words: \"Brilliant whodunit with stellar ensemble cast\"",
      "Review 2 has 6 words: \"Mystery crafted to absolute perfection here\"",
      "Review 3 has 6 words: \"Daniel Craig's accent steals every scene\"",
      "Review 4 has 6 words: \"Witty dialogue keeps you constantly engaged\"",
      "Review 5 has 6 words: \"Plot twists genuinely shocked me completely\"",
      "Review 6 has 6 words: \"Modern Agatha Christie done absolutely right\"",
      "Review 7 has 6 words: \"Cleverly subverts all murder mystery expectations\"",
      "Review 8 has 7 words: \"Ana de Armas delivers phenomenal breakthrough performance\"",
      "Review 9 has 6 words: \"Sharp social commentary disguised as entertainment\"",
      "Review 10 has 6 words: \"Rian Johnson proves his directorial genius\"",
      "Review 11 has 6 words: \"Every character feels perfectly developed throughout\"",
      "Review 12 has 6 words: \"Rewatchable mystery reveals new clues constantly\"",
      "Review 13 has 6 words: \"Satisfying conclusion ties everything together beautifully\"",
      "Review 14 has 6 words: \"Humor balances suspense in perfect harmony\"",
      "Review 15 has 6 words: \"Christopher Plummer's final performance shines bright\"",
      "Review 16 has 6 words: \"Class warfare themes executed with subtlety\"",
      "Review 17 has 6 words: \"Benoit Blanc deserves his own franchise\"",
      "Review 18 has 6 words: \"Smart script respects audience's intelligence completely\"",
      "Review 19 has 6 words: \"Visual storytelling enhances every single scene\"",
      "Review 20 has 6 words: \"Deserves all the critical acclaim received\""
    ]
  },
  "wordFrequency": {
    "brilliant": 1,
    "whodunit": 1,
    "stellar": 1,
    "ensemble": 1,
    "cast": 1,
    "mystery": 3,
    "crafted": 1,
    "absolute": 1,
    "perfection": 1,
    "here": 1,
    "daniel": 1,
    "craig's": 1,
    "accent": 1,
    "steals": 1,
    "witty": 1,
    "dialogue": 1,
    "constantly": 2,
    "engaged": 1,
    "twists": 1,
    "genuinely": 1,
    "shocked": 1,
    "modern": 1,
    "agatha": 1,
    "christie": 1,
    "done": 1,
    "right": 1,
    "cleverly": 1,
    "subverts": 1,
    "murder": 1,
    "expectations": 1,
    "ana": 1,
    "de": 1,
    "armas": 1,
    "delivers": 1,
    "phenomenal": 1,
    "breakthrough": 1,
    "performance": 2,
    "sharp": 1,
    "social": 1,
    "commentary": 1,
    "disguised": 1,
    "entertainment": 1,
    "rian": 1,
    "johnson": 1,
    "proves": 1,
    "directorial": 1,
    "genius": 1,
    "perfectly": 1,
    "developed": 1,
    "throughout": 1,
    "rewatchable": 1,
    "reveals": 1,
    "new": 1,
    "clues": 1,
    "satisfying": 1,
    "conclusion": 1,
    "ties": 1,
    "everything": 1,
    "together": 1,
    "beautifully": 1,
    "humor": 1,
    "balances": 1,
    "suspense": 1,
    "perfect": 1,
    "harmony": 1,
    "christopher": 1,
    "plummer's": 1,
    "final": 1,
    "shines": 1,
    "bright": 1,
    "class": 1,
    "warfare": 1,
    "themes": 1,
    "executed": 1,
    "subtlety": 1,
    "benoit": 1,
    "blanc": 1,
    "deserves": 2,
    "franchise": 1,
    "smart": 1,
    "script": 1,
    "respects": 1,
    "audience's": 1,
    "intelligence": 1,
    "visual": 1,
    "storytelling": 1,
    "enhances": 1,
    "single": 1,
    "critical": 1,
    "acclaim": 1,
    "received": 1
  },
  "topWords": [
    "mystery",
    "constantly",
    "performance",
    "deserves",
    "brilliant"
  ],
  "processedAt": "2026-02-07T10:59:04.018Z"
}