{
  "movieId": 718821,
  "title": "Twisters",
  "generatedAt": "2026-02-07T10:52:32.743Z",
  "reviews": [
    "Tornado thrills delivered with style",
    "Edge of seat weather mayhem",
    "Spectacular storm sequences stole show",
    "Adrenaline pumping disaster movie excellence",
    "Visual effects absolutely mind blowing",
    "Heart pounding from start finish",
    "Intense weather drama kept engaged",
    "Phenomenal cinematography captured nature's fury",
    "Gripping atmospheric tension throughout film",
    "Outstanding storm chasing adventure ride",
    "Breathtaking tornado scenes incredibly realistic",
    "Electrifying weather thriller exceeded expectations",
    "Masterfully crafted natural disaster spectacle",
    "Riveting storm sequences genuinely terrifying",
    "Impressive practical effects enhanced realism",
    "Compelling characters amid chaotic weather",
    "Visceral tornado encounters left speechless",
    "Expertly directed weather phenomenon thriller",
    "Stunning visual feast for eyes",
    "Unforgettable meteorological mayhem experience delivered"
  ],
  "validation": {
    "totalReviews": 20,
    "validFiveWord": 20,
    "issues": []
  },
  "wordFrequency": {
    "tornado": 3,
    "thrills": 1,
    "delivered": 2,
    "style": 1,
    "edge": 1,
    "seat": 1,
    "weather": 5,
    "mayhem": 2,
    "spectacular": 1,
    "storm": 3,
    "sequences": 2,
    "stole": 1,
    "show": 1,
    "adrenaline": 1,
    "pumping": 1,
    "disaster": 2,
    "excellence": 1,
    "visual": 2,
    "effects": 2,
    "mind": 1,
    "blowing": 1,
    "heart": 1,
    "pounding": 1,
    "start": 1,
    "finish": 1,
    "intense": 1,
    "drama": 1,
    "engaged": 1,
    "phenomenal": 1,
    "cinematography": 1,
    "captured": 1,
    "nature's": 1,
    "fury": 1,
    "gripping": 1,
    "atmospheric": 1,
    "tension": 1,
    "throughout": 1,
    "outstanding": 1,
    "chasing": 1,
    "adventure": 1,
    "ride": 1,
    "breathtaking": 1,
    "incredibly": 1,
    "realistic": 1,
    "electrifying": 1,
    "thriller": 2,
    "exceeded": 1,
    "expectations": 1,
    "masterfully": 1,
    "crafted": 1,
    "natural": 1,
    "spectacle": 1,
    "riveting": 1,
    "genuinely": 1,
    "terrifying": 1,
    "impressive": 1,
    "practical": 1,
    "enhanced": 1,
    "realism": 1,
    "compelling": 1,
    "amid": 1,
    "chaotic": 1,
    "visceral": 1,
    "encounters": 1,
    "left": 1,
    "speechless": 1,
    "expertly": 1,
    "directed": 1,
    "phenomenon": 1,
    "stunning": 1,
    "feast": 1,
    "eyes": 1,
    "unforgettable": 1,
    "meteorological": 1,
    "experience": 1,
    "edge-of-seat": 1,
    "mind-blowing": 1,
    "storm-sequences": 2
  },
  "topWords": [
    "weather",
    "tornado",
    "storm",
    "delivered",
    "mayhem"
  ],
  "processedAt": "2026-02-07T10:59:04.292Z"
}